pyjob/__init__.py
pyjob/details.py
pyjob/search.py
pyjob/search_test.py
pyjob/cli/__init__.py
pyjob/cli/main.py
pyjob_jdockerty-0.1.2.dist-info/LICENSE
pyjob_jdockerty-0.1.2.dist-info/METADATA
pyjob_jdockerty-0.1.2.dist-info/WHEEL
pyjob_jdockerty-0.1.2.dist-info/entry_points.txt
pyjob_jdockerty-0.1.2.dist-info/top_level.txt
pyjob_jdockerty-0.1.2.dist-info/RECORD
