Metadata-Version: 2.1
Name: pyjob-jdockerty
Version: 0.1.2
Summary: Job searching through code, interaction to the Reed API.
Home-page: https://github.com/jdockerty/pyjob
Author: jdockerty
License: UNKNOWN
Platform: UNKNOWN
Classifier: Programming Language :: Python :: 3
Classifier: License :: OSI Approved :: MIT License
Classifier: Operating System :: OS Independent
Requires-Dist: Click
Requires-Dist: loguru
Requires-Dist: pyjob
